awkexercises/__init__.py
awkexercises/app_guide.md
awkexercises/awk_exercises.css
awkexercises/awk_exercises.py
awkexercises/questions.json
awkexercises/user_progress.json
awkexercises/sample_input/addr.txt
awkexercises/sample_input/anchors.txt
awkexercises/sample_input/brackets.txt
awkexercises/sample_input/broken.txt
awkexercises/sample_input/concat.txt
awkexercises/sample_input/copyright.txt
awkexercises/sample_input/criteria.txt
awkexercises/sample_input/f1.txt
awkexercises/sample_input/f10.txt
awkexercises/sample_input/f11.txt
awkexercises/sample_input/f2.txt
awkexercises/sample_input/f3.txt
awkexercises/sample_input/f4.txt
awkexercises/sample_input/f5.txt
awkexercises/sample_input/f6.txt
awkexercises/sample_input/f7.txt
awkexercises/sample_input/f8.txt
awkexercises/sample_input/f9.txt
awkexercises/sample_input/fields.txt
awkexercises/sample_input/files.txt
awkexercises/sample_input/fw.txt
awkexercises/sample_input/hex.txt
awkexercises/sample_input/ip.txt
awkexercises/sample_input/items.txt
awkexercises/sample_input/jumbled.txt
awkexercises/sample_input/lines.txt
awkexercises/sample_input/match_words.txt
awkexercises/sample_input/mixed_fs.txt
awkexercises/sample_input/names.txt
awkexercises/sample_input/nums.txt
awkexercises/sample_input/nums1.txt
awkexercises/sample_input/odd.txt
awkexercises/sample_input/patterns.txt
awkexercises/sample_input/quoted.txt
awkexercises/sample_input/result.csv
awkexercises/sample_input/sample.txt
awkexercises/sample_input/scores.csv
awkexercises/sample_input/secrets.txt
awkexercises/sample_input/sum.txt
awkexercises/sample_input/table.txt
awkexercises/sample_input/twos.txt
awkexercises/sample_input/varying_fields.txt
awkexercises-1.7.0.dist-info/METADATA
awkexercises-1.7.0.dist-info/WHEEL
awkexercises-1.7.0.dist-info/entry_points.txt
awkexercises-1.7.0.dist-info/licenses/LICENSE
awkexercises-1.7.0.dist-info/RECORD
